pullboy/__init__.py
pullboy-0.94.dist-info/METADATA
pullboy-0.94.dist-info/RECORD
pullboy-0.94.dist-info/WHEEL
pullboy-0.94.dist-info/entry_points.txt
pullboy-0.94.dist-info/top_level.txt
