Metadata-Version: 2.1
Name: pullboy
Version: 0.94
Summary: Super Simple Auto-Deployment server
Home-page: http://github.com/theSage21/pullboy
Author: Arjoonn Sharma
Author-email: arjoonn.94@gmail.com
License: UNKNOWN
Keywords: pullboy,auto deploy server
Platform: UNKNOWN
Requires-Dist: bottle
Requires-Dist: pyyaml
